{"spotify:album:0lrmy4pJINsFzycJvttX2W": [{"n": 1, "name": "Marilyn Monroe", "uri": "spotify:track:5KmJMi7MiBJtCeJ08lmKzo", "ms": 351470}, {"n": 1, "name": "Marilyn Monroe", "uri": "spotify:track:5KmJMi7MiBJtCeJ08lmKzo", "ms": 351470}, {"n": 2, "name": "Brand New (with Justin Timberlake)", "uri": "spotify:track:1RUubW9fHtIYwjl588PrhZ", "ms": 271711}, {"n": 2, "name": "Brand New (with Justin Timberlake)", "uri": "spotify:track:1RUubW9fHtIYwjl588PrhZ", "ms": 271711}, {"n": 3, "name": "Hunter", "uri": "spotify:track:6xATKzdUO89mZvStODhUSR", "ms": 240934}, {"n": 3, "name": "Hunter", "uri": "spotify:track:6xATKzdUO89mZvStODhUSR", "ms": 240934}, {"n": 4, "name": "Gush", "uri": "spotify:track:0Aj49rBA0sepKeOpxE4Rdz", "ms": 234677}, {"n": 4, "name": "Gush", "uri": "spotify:track:0Aj49rBA0sepKeOpxE4Rdz", "ms": 234677}, {"n": 5, "name": "Happy - From \"Despicable Me 2\"", "uri": "spotify:track:60nZcImufyMA1MKQY3dcCH", "ms": 233306}, {"n": 5, "name": "Happy - From \"Despicable Me 2\"", "uri": "spotify:track:60nZcImufyMA1MKQY3dcCH", "ms": 233306}, {"n": 6, "name": "Come Get It Bae", "uri": "spotify:track:24MSdaNRlLgjp8xYeJeXwZ", "ms": 201944}, {"n": 6, "name": "Come Get It Bae", "uri": "spotify:track:24MSdaNRlLgjp8xYeJeXwZ", "ms": 201944}, {"n": 7, "name": "Gust of Wind", "uri": "spotify:track:5m6F6glTwHhsolaKD0gGu0", "ms": 285619}, {"n": 7, "name": "Gust of Wind", "uri": "spotify:track:5m6F6glTwHhsolaKD0gGu0", "ms": 285619}, {"n": 8, "name": "Lost Queen", "uri": "spotify:track:2SYCj35WXBydywsRJl91cE", "ms": 476632}, {"n": 8, "name": "Lost Queen", "uri": "spotify:track:2SYCj35WXBydywsRJl91cE", "ms": 476632}, {"n": 9, "name": "Know Who You Are (with Alicia Keys)", "uri": "spotify:track:3dhFRC4YORTaOlRhB9f8Ys", "ms": 236923}, {"n": 9, "name": "Know Who You Are (with Alicia Keys)", "uri": "spotify:track:3dhFRC4YORTaOlRhB9f8Ys", "ms": 236923}, {"n": 10, "name": "It Girl", "uri": "spotify:track:4nLHTIo4DqpCvD2EiLKhtJ", "ms": 287371}, {"n": 10, "name": "It Girl", "uri": "spotify:track:4nLHTIo4DqpCvD2EiLKhtJ", "ms": 287371}, {"n": 11, "name": "Smile", "uri": "spotify:track:1CtBWfrEodNcQNebJXK7lG", "ms": 226244}, {"n": 11, "name": "Smile", "uri": "spotify:track:1CtBWfrEodNcQNebJXK7lG", "ms": 226244}], "spotify:album:2ODvWsOgouMbaA5xf0RkJe": [{"n": 1, "name": "Starboy", "uri": "spotify:track:7MXVkk9YMctZqd1Srtv4MB", "ms": 230453}, {"n": 1, "name": "Starboy", "uri": "spotify:track:7MXVkk9YMctZqd1Srtv4MB", "ms": 230453}, {"n": 2, "name": "Party Monster", "uri": "spotify:track:4F7A0DXBrmUAkp32uenhZt", "ms": 249213}, {"n": 2, "name": "Party Monster", "uri": "spotify:track:4F7A0DXBrmUAkp32uenhZt", "ms": 249213}, {"n": 3, "name": "False Alarm", "uri": "spotify:track:4oeaIftdpT3JuZLcCkKmVE", "ms": 220306}, {"n": 3, "name": "False Alarm", "uri": "spotify:track:4oeaIftdpT3JuZLcCkKmVE", "ms": 220306}, {"n": 4, "name": "Reminder", "uri": "spotify:track:37F0uwRSrdzkBiuj0D5UHI", "ms": 218880}, {"n": 4, "name": "Reminder", "uri": "spotify:track:37F0uwRSrdzkBiuj0D5UHI", "ms": 218880}, {"n": 5, "name": "Rockin\u2019", "uri": "spotify:track:36YCdzT57us0LhDmCYtrNE", "ms": 232880}, {"n": 5, "name": "Rockin\u2019", "uri": "spotify:track:36YCdzT57us0LhDmCYtrNE", "ms": 232880}, {"n": 6, "name": "Secrets", "uri": "spotify:track:00NAQYOP4AmWR549nnYJZu", "ms": 265600}, {"n": 6, "name": "Secrets", "uri": "spotify:track:00NAQYOP4AmWR549nnYJZu", "ms": 265600}, {"n": 7, "name": "True Colors", "uri": "spotify:track:1oGdVdYjeQvojGKDddxLQQ", "ms": 206013}, {"n": 7, "name": "True Colors", "uri": "spotify:track:1oGdVdYjeQvojGKDddxLQQ", "ms": 206013}, {"n": 8, "name": "Stargirl Interlude", "uri": "spotify:track:4EDijkJdHBZZ0GwJ12iTAj", "ms": 111640}, {"n": 8, "name": "Stargirl Interlude", "uri": "spotify:track:4EDijkJdHBZZ0GwJ12iTAj", "ms": 111640}, {"n": 9, "name": "Sidewalks", "uri": "spotify:track:4h90qkbnW1Qq6pBhoPvwko", "ms": 231360}, {"n": 9, "name": "Sidewalks", "uri": "spotify:track:4h90qkbnW1Qq6pBhoPvwko", "ms": 231360}, {"n": 10, "name": "Six Feet Under", "uri": "spotify:track:4mU5iXHeLgbR94siF7p1sY", "ms": 237573}, {"n": 10, "name": "Six Feet Under", "uri": "spotify:track:4mU5iXHeLgbR94siF7p1sY", "ms": 237573}, {"n": 11, "name": "Love To Lay", "uri": "spotify:track:27BgDmciSjoxTG0almHTpZ", "ms": 223293}, {"n": 11, "name": "Love To Lay", "uri": "spotify:track:27BgDmciSjoxTG0almHTpZ", "ms": 223293}, {"n": 12, "name": "A Lonely Night", "uri": "spotify:track:0ifooM33X1iBxVYyOkSbXW", "ms": 220173}, {"n": 12, "name": "A Lonely Night", "uri": "spotify:track:0ifooM33X1iBxVYyOkSbXW", "ms": 220173}, {"n": 13, "name": "Attention", "uri": "spotify:track:6pDVjCUA3B1vg9waKutAsv", "ms": 197653}, {"n": 13, "name": "Attention", "uri": "spotify:track:6pDVjCUA3B1vg9waKutAsv", "ms": 197653}, {"n": 14, "name": "Ordinary Life", "uri": "spotify:track:15k2nBQJ0teDmPZHrOXL2N", "ms": 221920}, {"n": 14, "name": "Ordinary Life", "uri": "spotify:track:15k2nBQJ0teDmPZHrOXL2N", "ms": 221920}, {"n": 15, "name": "Nothing Without You", "uri": "spotify:track:57qiTKh8bVX0VtfUNTQqhw", "ms": 198653}, {"n": 15, "name": "Nothing Without You", "uri": "spotify:track:57qiTKh8bVX0VtfUNTQqhw", "ms": 198653}, {"n": 16, "name": "All I Know", "uri": "spotify:track:0NWqNXBJTpXbkI5rPWNy3p", "ms": 321026}, {"n": 16, "name": "All I Know", "uri": "spotify:track:0NWqNXBJTpXbkI5rPWNy3p", "ms": 321026}, {"n": 17, "name": "Die For You", "uri": "spotify:track:2Ch7LmS7r2Gy2kc64wv3Bz", "ms": 260252}, {"n": 17, "name": "Die For You", "uri": "spotify:track:2Ch7LmS7r2Gy2kc64wv3Bz", "ms": 260252}, {"n": 18, "name": "I Feel It Coming", "uri": "spotify:track:3dhjNA0jGA8vHBQ1VdD6vV", "ms": 269186}, {"n": 18, "name": "I Feel It Coming", "uri": "spotify:track:3dhjNA0jGA8vHBQ1VdD6vV", "ms": 269186}], "spotify:album:2noRn2Aes5aoNVsU6iWThc": [{"n": 1, "name": "One More Time", "uri": "spotify:track:0DiWol3AO6WpXZgp0goxAV", "ms": 320357}, {"n": 1, "name": "One More Time", "uri": "spotify:track:0DiWol3AO6WpXZgp0goxAV", "ms": 320357}, {"n": 2, "name": "Aerodynamic", "uri": "spotify:track:3H3cOQ6LBLSvmcaV7QkZEu", "ms": 212546}, {"n": 2, "name": "Aerodynamic", "uri": "spotify:track:3H3cOQ6LBLSvmcaV7QkZEu", "ms": 212546}, {"n": 3, "name": "Digital Love", "uri": "spotify:track:2VEZx7NWsZ1D0eJ4uv5Fym", "ms": 301373}, {"n": 3, "name": "Digital Love", "uri": "spotify:track:2VEZx7NWsZ1D0eJ4uv5Fym", "ms": 301373}, {"n": 4, "name": "Harder, Better, Faster, Stronger", "uri": "spotify:track:5W3cjX2J3tjhG8zb6u0qHn", "ms": 226413}, {"n": 4, "name": "Harder, Better, Faster, Stronger", "uri": "spotify:track:5W3cjX2J3tjhG8zb6u0qHn", "ms": 226413}, {"n": 5, "name": "Crescendolls", "uri": "spotify:track:6vuPZX9fWESg5js2JFTQRJ", "ms": 211640}, {"n": 5, "name": "Crescendolls", "uri": "spotify:track:6vuPZX9fWESg5js2JFTQRJ", "ms": 211640}, {"n": 6, "name": "Nightvision", "uri": "spotify:track:63JXZZRbmzooashakb0zbu", "ms": 104466}, {"n": 6, "name": "Nightvision", "uri": "spotify:track:63JXZZRbmzooashakb0zbu", "ms": 104466}, {"n": 7, "name": "Superheroes", "uri": "spotify:track:186hvCTyrni4KT9nwIQ7zS", "ms": 237800}, {"n": 7, "name": "Superheroes", "uri": "spotify:track:186hvCTyrni4KT9nwIQ7zS", "ms": 237800}, {"n": 8, "name": "High Life", "uri": "spotify:track:098ttCNmncrO4YvqWUNMvn", "ms": 201800}, {"n": 8, "name": "High Life", "uri": "spotify:track:098ttCNmncrO4YvqWUNMvn", "ms": 201800}, {"n": 9, "name": "Something About Us", "uri": "spotify:track:1NeLwFETswx8Fzxl2AFl91", "ms": 232666}, {"n": 9, "name": "Something About Us", "uri": "spotify:track:1NeLwFETswx8Fzxl2AFl91", "ms": 232666}, {"n": 10, "name": "Voyager", "uri": "spotify:track:7cMFjxhbXBpOlais7KMF3j", "ms": 227866}, {"n": 10, "name": "Voyager", "uri": "spotify:track:7cMFjxhbXBpOlais7KMF3j", "ms": 227866}, {"n": 11, "name": "Veridis Quo", "uri": "spotify:track:2LD2gT7gwAurzdQDQtILds", "ms": 345186}, {"n": 11, "name": "Veridis Quo", "uri": "spotify:track:2LD2gT7gwAurzdQDQtILds", "ms": 345186}, {"n": 12, "name": "Short Circuit", "uri": "spotify:track:4npMbTuxrUA3Wd7edACZ2L", "ms": 206866}, {"n": 12, "name": "Short Circuit", "uri": "spotify:track:4npMbTuxrUA3Wd7edACZ2L", "ms": 206866}, {"n": 13, "name": "Face to Face", "uri": "spotify:track:7v9Q0dAb9t7h8gJOkcJHay", "ms": 240173}, {"n": 13, "name": "Face to Face", "uri": "spotify:track:7v9Q0dAb9t7h8gJOkcJHay", "ms": 240173}, {"n": 14, "name": "Too Long", "uri": "spotify:track:3zMvotMEQK3xvH01vA9wAP", "ms": 600293}, {"n": 14, "name": "Too Long", "uri": "spotify:track:3zMvotMEQK3xvH01vA9wAP", "ms": 600293}], "spotify:album:3AMXFnwHWXCvNr5NCCpLZI": [{"n": 1, "name": "Overture", "uri": "spotify:track:4uXQXq2AH6mAB8gvTzNUab", "ms": 148006}, {"n": 1, "name": "Overture", "uri": "spotify:track:4uXQXq2AH6mAB8gvTzNUab", "ms": 148006}, {"n": 2, "name": "The Grid", "uri": "spotify:track:2tRWMCijEFsGPDxBgHxHre", "ms": 96739}, {"n": 2, "name": "The Grid", "uri": "spotify:track:2tRWMCijEFsGPDxBgHxHre", "ms": 96739}, {"n": 3, "name": "The Son of Flynn", "uri": "spotify:track:3zL0LAsSh3dTO73dSOKWkr", "ms": 95226}, {"n": 3, "name": "The Son of Flynn", "uri": "spotify:track:3zL0LAsSh3dTO73dSOKWkr", "ms": 95226}, {"n": 4, "name": "Recognizer", "uri": "spotify:track:6dooKqgWKBVwQLLarxJPDM", "ms": 157719}, {"n": 4, "name": "Recognizer", "uri": "spotify:track:6dooKqgWKBVwQLLarxJPDM", "ms": 157719}, {"n": 5, "name": "Armory", "uri": "spotify:track:6NbukMzsdx888nymIiWKlV", "ms": 122975}, {"n": 5, "name": "Armory", "uri": "spotify:track:6NbukMzsdx888nymIiWKlV", "ms": 122975}, {"n": 6, "name": "Arena", "uri": "spotify:track:4csD9dmdLHnarNyu1wG8Iv", "ms": 93236}, {"n": 6, "name": "Arena", "uri": "spotify:track:4csD9dmdLHnarNyu1wG8Iv", "ms": 93236}, {"n": 7, "name": "Rinzler", "uri": "spotify:track:70RkgofUfQHLl2FT2Mx5zq", "ms": 137635}, {"n": 7, "name": "Rinzler", "uri": "spotify:track:70RkgofUfQHLl2FT2Mx5zq", "ms": 137635}, {"n": 8, "name": "The Game Has Changed", "uri": "spotify:track:1LaCW0R8Q7oIY3tKtDgZOw", "ms": 205474}, {"n": 8, "name": "The Game Has Changed", "uri": "spotify:track:1LaCW0R8Q7oIY3tKtDgZOw", "ms": 205474}, {"n": 9, "name": "Outlands", "uri": "spotify:track:1lQZ7fJRndezv3hnEtadcI", "ms": 162501}, {"n": 9, "name": "Outlands", "uri": "spotify:track:1lQZ7fJRndezv3hnEtadcI", "ms": 162501}, {"n": 10, "name": "Adagio For TRON", "uri": "spotify:track:6c9LokX8oCb3c3VT0Ok0ep", "ms": 251070}, {"n": 10, "name": "Adagio For TRON", "uri": "spotify:track:6c9LokX8oCb3c3VT0Ok0ep", "ms": 251070}, {"n": 11, "name": "Nocturne", "uri": "spotify:track:7toH0mW6Noyt5B0nczGqj5", "ms": 101688}, {"n": 11, "name": "Nocturne", "uri": "spotify:track:7toH0mW6Noyt5B0nczGqj5", "ms": 101688}, {"n": 12, "name": "End of Line", "uri": "spotify:track:09TlxralXOGX35LUutvw7I", "ms": 156486}, {"n": 12, "name": "End of Line", "uri": "spotify:track:09TlxralXOGX35LUutvw7I", "ms": 156486}, {"n": 13, "name": "Derezzed", "uri": "spotify:track:7hqlHZIXhwAzpWQxm9KzBd", "ms": 104113}, {"n": 13, "name": "Derezzed", "uri": "spotify:track:7hqlHZIXhwAzpWQxm9KzBd", "ms": 104113}, {"n": 14, "name": "Fall", "uri": "spotify:track:5pPKx6IhpBIqdMGAC0RYn9", "ms": 82605}, {"n": 14, "name": "Fall", "uri": "spotify:track:5pPKx6IhpBIqdMGAC0RYn9", "ms": 82605}, {"n": 15, "name": "Solar Sailer", "uri": "spotify:track:770xg19bhZii0ARFBn1qR5", "ms": 162126}, {"n": 15, "name": "Solar Sailer", "uri": "spotify:track:770xg19bhZii0ARFBn1qR5", "ms": 162126}, {"n": 16, "name": "Rectifier", "uri": "spotify:track:6lEEO57pUsxL33F3tSNWV3", "ms": 134047}, {"n": 16, "name": "Rectifier", "uri": "spotify:track:6lEEO57pUsxL33F3tSNWV3", "ms": 134047}, {"n": 17, "name": "Disc Wars", "uri": "spotify:track:1OAEosQeqo1Q2RKkipkkiP", "ms": 251453}, {"n": 17, "name": "Disc Wars", "uri": "spotify:track:1OAEosQeqo1Q2RKkipkkiP", "ms": 251453}, {"n": 18, "name": "C.L.U.", "uri": "spotify:track:5yq0Wr88ARxysyYEEfVY2E", "ms": 279313}, {"n": 18, "name": "C.L.U.", "uri": "spotify:track:5yq0Wr88ARxysyYEEfVY2E", "ms": 279313}, {"n": 19, "name": "Arrival", "uri": "spotify:track:4Fm7MMYiSRriB4eTvulVKQ", "ms": 120489}, {"n": 19, "name": "Arrival", "uri": "spotify:track:4Fm7MMYiSRriB4eTvulVKQ", "ms": 120489}, {"n": 20, "name": "Flynn Lives", "uri": "spotify:track:3szggCvjcOLWroR6DM9cJn", "ms": 202150}, {"n": 20, "name": "Flynn Lives", "uri": "spotify:track:3szggCvjcOLWroR6DM9cJn", "ms": 202150}, {"n": 21, "name": "TRON Legacy (End Titles)", "uri": "spotify:track:69T9xcz6U8GFYmdPLkYn4J", "ms": 197825}, {"n": 21, "name": "TRON Legacy (End Titles)", "uri": "spotify:track:69T9xcz6U8GFYmdPLkYn4J", "ms": 197825}, {"n": 22, "name": "Finale", "uri": "spotify:track:2URbRukS6KLiQOGAhGP40J", "ms": 262779}, {"n": 22, "name": "Finale", "uri": "spotify:track:2URbRukS6KLiQOGAhGP40J", "ms": 262779}, {"n": 23, "name": "Sea of Simulation", "uri": "spotify:track:1dsetWQ7Jx0uygKHPH0GBk", "ms": 160659}, {"n": 23, "name": "Sea of Simulation", "uri": "spotify:track:1dsetWQ7Jx0uygKHPH0GBk", "ms": 160659}, {"n": 24, "name": "Encom Part II", "uri": "spotify:track:37OFlKZy7bJeF6vzFmekfK", "ms": 136760}, {"n": 24, "name": "Encom Part II", "uri": "spotify:track:37OFlKZy7bJeF6vzFmekfK", "ms": 136760}, {"n": 25, "name": "Encom Part I", "uri": "spotify:track:0wuXtDn3vPxvG6szydUznc", "ms": 231680}, {"n": 25, "name": "Encom Part I", "uri": "spotify:track:0wuXtDn3vPxvG6szydUznc", "ms": 231680}, {"n": 26, "name": "Round One", "uri": "spotify:track:0wF6Fj7kEhrfVWC3AgCRBx", "ms": 100026}, {"n": 26, "name": "Round One", "uri": "spotify:track:0wF6Fj7kEhrfVWC3AgCRBx", "ms": 100026}, {"n": 27, "name": "Castor", "uri": "spotify:track:6w5ZzNX84SzG5ob8tm4Ozq", "ms": 138506}, {"n": 27, "name": "Castor", "uri": "spotify:track:6w5ZzNX84SzG5ob8tm4Ozq", "ms": 138506}, {"n": 28, "name": "Reflections", "uri": "spotify:track:2Aq8H7LO9IujF4uFUaCpfj", "ms": 161300}, {"n": 28, "name": "Reflections", "uri": "spotify:track:2Aq8H7LO9IujF4uFUaCpfj", "ms": 161300}, {"n": 29, "name": "Sunrise Prelude", "uri": "spotify:track:5EkLu4IaWJuFfDlPdCtjQX", "ms": 171266}, {"n": 29, "name": "Sunrise Prelude", "uri": "spotify:track:5EkLu4IaWJuFfDlPdCtjQX", "ms": 171266}, {"n": 30, "name": "Father and Son", "uri": "spotify:track:5OO1MmnLVRPYjDGbDC9c5s", "ms": 189946}, {"n": 30, "name": "Father and Son", "uri": "spotify:track:5OO1MmnLVRPYjDGbDC9c5s", "ms": 189946}, {"n": 31, "name": "Outlands, Part II", "uri": "spotify:track:0KCzXogxEjPDOYrwvC7Dkg", "ms": 174200}, {"n": 31, "name": "Outlands, Part II", "uri": "spotify:track:0KCzXogxEjPDOYrwvC7Dkg", "ms": 174200}], "spotify:album:4GGazqHvuKwxBjWLFaJkDL": [{"n": 1, "name": "Genesis", "uri": "spotify:track:4wSmqFg31t6LsQWtzYAJob", "ms": 234960}, {"n": 1, "name": "Genesis", "uri": "spotify:track:4wSmqFg31t6LsQWtzYAJob", "ms": 234960}, {"n": 2, "name": "Let There Be Light", "uri": "spotify:track:7LG6dQGMIDFKV1SazzWGjK", "ms": 295946}, {"n": 2, "name": "Let There Be Light", "uri": "spotify:track:7LG6dQGMIDFKV1SazzWGjK", "ms": 295946}, {"n": 3, "name": "D.A.N.C.E.", "uri": "spotify:track:33yAEqzKXexYM3WlOYtTfQ", "ms": 242266}, {"n": 3, "name": "D.A.N.C.E.", "uri": "spotify:track:33yAEqzKXexYM3WlOYtTfQ", "ms": 242266}, {"n": 4, "name": "Newjack", "uri": "spotify:track:64KZZUapCQHba7jibt5yYQ", "ms": 216893}, {"n": 4, "name": "Newjack", "uri": "spotify:track:64KZZUapCQHba7jibt5yYQ", "ms": 216893}, {"n": 5, "name": "Phantom", "uri": "spotify:track:2weNFSRqkClXtfBPTteafY", "ms": 262266}, {"n": 5, "name": "Phantom", "uri": "spotify:track:2weNFSRqkClXtfBPTteafY", "ms": 262266}, {"n": 6, "name": "Phantom Pt. II", "uri": "spotify:track:2A3emhzbZo7eSvEUtAm3ZS", "ms": 200826}, {"n": 6, "name": "Phantom Pt. II", "uri": "spotify:track:2A3emhzbZo7eSvEUtAm3ZS", "ms": 200826}, {"n": 7, "name": "Valentine", "uri": "spotify:track:5Q6OXP4UlS1stbtGfBLZ9I", "ms": 176253}, {"n": 7, "name": "Valentine", "uri": "spotify:track:5Q6OXP4UlS1stbtGfBLZ9I", "ms": 176253}, {"n": 8, "name": "TTHHEE PPAARRTTYY", "uri": "spotify:track:1z4835vzYgbtb26uRWpGhq", "ms": 243426}, {"n": 8, "name": "TTHHEE PPAARRTTYY", "uri": "spotify:track:1z4835vzYgbtb26uRWpGhq", "ms": 243426}, {"n": 9, "name": "DVNO", "uri": "spotify:track:7pdDBqpilpdW7c40DpFMW9", "ms": 236133}, {"n": 9, "name": "DVNO", "uri": "spotify:track:7pdDBqpilpdW7c40DpFMW9", "ms": 236133}, {"n": 10, "name": "Stress", "uri": "spotify:track:1YdbiBOWvFUi6Zko3HXyEG", "ms": 298586}, {"n": 10, "name": "Stress", "uri": "spotify:track:1YdbiBOWvFUi6Zko3HXyEG", "ms": 298586}, {"n": 11, "name": "Waters of Nazareth", "uri": "spotify:track:0WGLjl3EIjf9MjJFJ90yX9", "ms": 265173}, {"n": 11, "name": "Waters of Nazareth", "uri": "spotify:track:0WGLjl3EIjf9MjJFJ90yX9", "ms": 265173}, {"n": 12, "name": "One Minute to Midnight", "uri": "spotify:track:6R0o9mEwZsYtqZsQrXYVOO", "ms": 220933}, {"n": 12, "name": "One Minute to Midnight", "uri": "spotify:track:6R0o9mEwZsYtqZsQrXYVOO", "ms": 220933}], "spotify:album:4m2880jivSbbyEGAKfITCa": [{"n": 1, "name": "Give Life Back to Music", "uri": "spotify:track:0dEIca2nhcxDUV8C5QkPYb", "ms": 275386}, {"n": 1, "name": "Give Life Back to Music", "uri": "spotify:track:0dEIca2nhcxDUV8C5QkPYb", "ms": 275386}, {"n": 2, "name": "The Game of Love", "uri": "spotify:track:3ctALmweZBapfBdFiIVpji", "ms": 322146}, {"n": 2, "name": "The Game of Love", "uri": "spotify:track:3ctALmweZBapfBdFiIVpji", "ms": 322146}, {"n": 3, "name": "Giorgio by Moroder", "uri": "spotify:track:0oks4FnzhNp5QPTZtoet7c", "ms": 544626}, {"n": 3, "name": "Giorgio by Moroder", "uri": "spotify:track:0oks4FnzhNp5QPTZtoet7c", "ms": 544626}, {"n": 4, "name": "Within", "uri": "spotify:track:7Bxv0WL7UC6WwQpk9TzdMJ", "ms": 228506}, {"n": 4, "name": "Within", "uri": "spotify:track:7Bxv0WL7UC6WwQpk9TzdMJ", "ms": 228506}, {"n": 5, "name": "Instant Crush (feat. Julian Casablancas)", "uri": "spotify:track:2cGxRwrMyEAp8dEbuZaVv6", "ms": 337560}, {"n": 5, "name": "Instant Crush (feat. Julian Casablancas)", "uri": "spotify:track:2cGxRwrMyEAp8dEbuZaVv6", "ms": 337560}, {"n": 6, "name": "Lose Yourself to Dance (feat. Pharrell Williams)", "uri": "spotify:track:5CMjjywI0eZMixPeqNd75R", "ms": 353893}, {"n": 6, "name": "Lose Yourself to Dance (feat. Pharrell Williams)", "uri": "spotify:track:5CMjjywI0eZMixPeqNd75R", "ms": 353893}, {"n": 7, "name": "Touch (feat. Paul Williams)", "uri": "spotify:track:7oaEjLP2dTJLJsITbAxTOz", "ms": 498960}, {"n": 7, "name": "Touch (feat. Paul Williams)", "uri": "spotify:track:7oaEjLP2dTJLJsITbAxTOz", "ms": 498960}, {"n": 8, "name": "Get Lucky (feat. Pharrell Williams and Nile Rodgers)", "uri": "spotify:track:69kOkLUCkxIZYexIgSG8rq", "ms": 369626}, {"n": 8, "name": "Get Lucky (feat. Pharrell Williams and Nile Rodgers)", "uri": "spotify:track:69kOkLUCkxIZYexIgSG8rq", "ms": 369626}, {"n": 9, "name": "Beyond", "uri": "spotify:track:0k1xMUwn9sb7bZiqdT9ygx", "ms": 290240}, {"n": 9, "name": "Beyond", "uri": "spotify:track:0k1xMUwn9sb7bZiqdT9ygx", "ms": 290240}, {"n": 10, "name": "Motherboard", "uri": "spotify:track:79koEJRtKOOGJ0VSAF3FMk", "ms": 341653}, {"n": 10, "name": "Motherboard", "uri": "spotify:track:79koEJRtKOOGJ0VSAF3FMk", "ms": 341653}, {"n": 11, "name": "Fragments of Time (feat. Todd Edwards)", "uri": "spotify:track:0IedgQjjJ8Ad4B3UDQ5Lyn", "ms": 279773}, {"n": 11, "name": "Fragments of Time (feat. Todd Edwards)", "uri": "spotify:track:0IedgQjjJ8Ad4B3UDQ5Lyn", "ms": 279773}, {"n": 12, "name": "Doin' it Right (feat. Panda Bear)", "uri": "spotify:track:36c4JohayB9qd64eidQMBi", "ms": 251293}, {"n": 12, "name": "Doin' it Right (feat. Panda Bear)", "uri": "spotify:track:36c4JohayB9qd64eidQMBi", "ms": 251293}, {"n": 13, "name": "Contact", "uri": "spotify:track:2KHRENHQzTIQ001nlP9Gdc", "ms": 383626}, {"n": 13, "name": "Contact", "uri": "spotify:track:2KHRENHQzTIQ001nlP9Gdc", "ms": 383626}], "spotify:album:5uRdvUR7xCnHmUW8n64n9y": [{"n": 1, "name": "Daftendirekt", "uri": "spotify:track:7fYIXtdOUl8WqXAqQGyIHQ", "ms": 164560}, {"n": 1, "name": "Daftendirekt", "uri": "spotify:track:7fYIXtdOUl8WqXAqQGyIHQ", "ms": 164560}, {"n": 2, "name": "WDPK 83.7 FM", "uri": "spotify:track:7dTWkvPOPgbGuMk4HDxNpY", "ms": 28333}, {"n": 2, "name": "WDPK 83.7 FM", "uri": "spotify:track:7dTWkvPOPgbGuMk4HDxNpY", "ms": 28333}, {"n": 3, "name": "Revolution 909", "uri": "spotify:track:5pgZpHqfv4TSomtkfGZGrG", "ms": 335026}, {"n": 3, "name": "Revolution 909", "uri": "spotify:track:5pgZpHqfv4TSomtkfGZGrG", "ms": 335026}, {"n": 4, "name": "Da Funk", "uri": "spotify:track:0MyY4WcN7DIfbSmp5yej5z", "ms": 328680}, {"n": 4, "name": "Da Funk", "uri": "spotify:track:0MyY4WcN7DIfbSmp5yej5z", "ms": 328680}, {"n": 5, "name": "Phoenix", "uri": "spotify:track:6nQy5XEEEJKu8FE1FS2Wbt", "ms": 297106}, {"n": 5, "name": "Phoenix", "uri": "spotify:track:6nQy5XEEEJKu8FE1FS2Wbt", "ms": 297106}, {"n": 6, "name": "Fresh", "uri": "spotify:track:78H72MElkOY9cRnaudxZFY", "ms": 244400}, {"n": 6, "name": "Fresh", "uri": "spotify:track:78H72MElkOY9cRnaudxZFY", "ms": 244400}, {"n": 7, "name": "Around the World", "uri": "spotify:track:1pKYYY0dkg23sQQXi0Q5zN", "ms": 429533}, {"n": 7, "name": "Around the World", "uri": "spotify:track:1pKYYY0dkg23sQQXi0Q5zN", "ms": 429533}, {"n": 8, "name": "Rollin' & Scratchin'", "uri": "spotify:track:6hgBJPTHoDJyxydmtFWHKf", "ms": 448626}, {"n": 8, "name": "Rollin' & Scratchin'", "uri": "spotify:track:6hgBJPTHoDJyxydmtFWHKf", "ms": 448626}, {"n": 9, "name": "Teachers", "uri": "spotify:track:4ZdjCuiWBv2weLftWPJ72c", "ms": 173493}, {"n": 9, "name": "Teachers", "uri": "spotify:track:4ZdjCuiWBv2weLftWPJ72c", "ms": 173493}, {"n": 10, "name": "High Fidelity", "uri": "spotify:track:63ZAmhkAV6Kaw955ohbEsN", "ms": 362466}, {"n": 10, "name": "High Fidelity", "uri": "spotify:track:63ZAmhkAV6Kaw955ohbEsN", "ms": 362466}, {"n": 11, "name": "Rock'n Roll", "uri": "spotify:track:1nluqUxDKnwWyScYVeQHXa", "ms": 453866}, {"n": 11, "name": "Rock'n Roll", "uri": "spotify:track:1nluqUxDKnwWyScYVeQHXa", "ms": 453866}, {"n": 12, "name": "Oh Yeah", "uri": "spotify:track:3Pm4jgrXCu0W7gTqyrlR4F", "ms": 121200}, {"n": 12, "name": "Oh Yeah", "uri": "spotify:track:3Pm4jgrXCu0W7gTqyrlR4F", "ms": 121200}, {"n": 13, "name": "Burnin'", "uri": "spotify:track:6nSOhDfZOulWp0pnEHFrnn", "ms": 414173}, {"n": 13, "name": "Burnin'", "uri": "spotify:track:6nSOhDfZOulWp0pnEHFrnn", "ms": 414173}, {"n": 14, "name": "Indo Silver Club", "uri": "spotify:track:4jF8GAMRCOenL17cNnBDI0", "ms": 274733}, {"n": 14, "name": "Indo Silver Club", "uri": "spotify:track:4jF8GAMRCOenL17cNnBDI0", "ms": 274733}, {"n": 15, "name": "Alive", "uri": "spotify:track:1PH5Es89c1cENU8WVuWwbp", "ms": 316253}, {"n": 15, "name": "Alive", "uri": "spotify:track:1PH5Es89c1cENU8WVuWwbp", "ms": 316253}, {"n": 16, "name": "Funk Ad", "uri": "spotify:track:0cjavaamK4gxP9iZYw5I2X", "ms": 51400}, {"n": 16, "name": "Funk Ad", "uri": "spotify:track:0cjavaamK4gxP9iZYw5I2X", "ms": 51400}], "spotify:album:7D2NdGvBHIavgLhmcwhluK": [{"n": 1, "name": "On Sight", "uri": "spotify:track:1gqkRc9WtOpnGIqxf2Hvzr", "ms": 156480}, {"n": 1, "name": "On Sight", "uri": "spotify:track:1gqkRc9WtOpnGIqxf2Hvzr", "ms": 156480}, {"n": 2, "name": "Black Skinhead", "uri": "spotify:track:722tgOgdIbNe3BEyLnejw4", "ms": 188013}, {"n": 2, "name": "Black Skinhead", "uri": "spotify:track:722tgOgdIbNe3BEyLnejw4", "ms": 188013}, {"n": 3, "name": "I Am A God", "uri": "spotify:track:0HMCdlOPJkAGlB0MlSWIcO", "ms": 231506}, {"n": 3, "name": "I Am A God", "uri": "spotify:track:0HMCdlOPJkAGlB0MlSWIcO", "ms": 231506}, {"n": 4, "name": "New Slaves", "uri": "spotify:track:4cAgkb0ifwn0FSHGXnr4F6", "ms": 256093}, {"n": 4, "name": "New Slaves", "uri": "spotify:track:4cAgkb0ifwn0FSHGXnr4F6", "ms": 256093}, {"n": 5, "name": "Hold My Liquor", "uri": "spotify:track:5nIu0VwPOsjkF61zfevLKh", "ms": 326946}, {"n": 5, "name": "Hold My Liquor", "uri": "spotify:track:5nIu0VwPOsjkF61zfevLKh", "ms": 326946}, {"n": 6, "name": "I'm In It", "uri": "spotify:track:52NmkyHsGsHGb1UX8fTkMg", "ms": 234853}, {"n": 6, "name": "I'm In It", "uri": "spotify:track:52NmkyHsGsHGb1UX8fTkMg", "ms": 234853}, {"n": 7, "name": "Blood On The Leaves", "uri": "spotify:track:42GcjriRK6srwHkfbkBqVl", "ms": 359800}, {"n": 7, "name": "Blood On The Leaves", "uri": "spotify:track:42GcjriRK6srwHkfbkBqVl", "ms": 359800}, {"n": 8, "name": "Guilt Trip", "uri": "spotify:track:5nPOM0nFRAJ3XI8xCxNAzO", "ms": 243746}, {"n": 8, "name": "Guilt Trip", "uri": "spotify:track:5nPOM0nFRAJ3XI8xCxNAzO", "ms": 243746}, {"n": 9, "name": "Send It Up", "uri": "spotify:track:3RKblQNJs8HPvWBgXmq6nn", "ms": 178040}, {"n": 9, "name": "Send It Up", "uri": "spotify:track:3RKblQNJs8HPvWBgXmq6nn", "ms": 178040}, {"n": 10, "name": "Bound 2", "uri": "spotify:track:3sNVsP50132BTNlImLx70i", "ms": 229146}, {"n": 10, "name": "Bound 2", "uri": "spotify:track:3sNVsP50132BTNlImLx70i", "ms": 229146}], "spotify:album:7g4qoHjkYvfFkXJEZCjtc1": [{"n": 1, "name": "Lisztomania", "uri": "spotify:track:4esUVfYnFcCCVHntx9FQCb", "ms": 241640}, {"n": 1, "name": "Lisztomania", "uri": "spotify:track:4esUVfYnFcCCVHntx9FQCb", "ms": 241640}, {"n": 1, "name": "Lisztomania", "uri": "spotify:track:4esUVfYnFcCCVHntx9FQCb", "ms": 241640}, {"n": 1, "name": "Lisztomania", "uri": "spotify:track:4esUVfYnFcCCVHntx9FQCb", "ms": 241640}, {"n": 2, "name": "1901", "uri": "spotify:track:68hYdj3GepWm2R202KhJT7", "ms": 193106}, {"n": 2, "name": "1901", "uri": "spotify:track:68hYdj3GepWm2R202KhJT7", "ms": 193106}, {"n": 2, "name": "1901", "uri": "spotify:track:68hYdj3GepWm2R202KhJT7", "ms": 193106}, {"n": 2, "name": "1901", "uri": "spotify:track:68hYdj3GepWm2R202KhJT7", "ms": 193106}, {"n": 3, "name": "Fences", "uri": "spotify:track:4N7159SXtxwObOFhimCLGW", "ms": 224973}, {"n": 3, "name": "Fences", "uri": "spotify:track:4N7159SXtxwObOFhimCLGW", "ms": 224973}, {"n": 3, "name": "Fences", "uri": "spotify:track:4N7159SXtxwObOFhimCLGW", "ms": 224973}, {"n": 3, "name": "Fences", "uri": "spotify:track:4N7159SXtxwObOFhimCLGW", "ms": 224973}, {"n": 4, "name": "Love Like a Sunset, Pt. I", "uri": "spotify:track:25wmDyqurSaUc7RB6SUIHT", "ms": 338546}, {"n": 4, "name": "Love Like a Sunset, Pt. I", "uri": "spotify:track:25wmDyqurSaUc7RB6SUIHT", "ms": 338546}, {"n": 4, "name": "Love Like a Sunset, Pt. I", "uri": "spotify:track:25wmDyqurSaUc7RB6SUIHT", "ms": 338546}, {"n": 4, "name": "Love Like a Sunset, Pt. I", "uri": "spotify:track:25wmDyqurSaUc7RB6SUIHT", "ms": 338546}, {"n": 5, "name": "Love Like a Sunset, Pt. II", "uri": "spotify:track:4S5kWaB3e1dsgKBGgxfNgQ", "ms": 116720}, {"n": 5, "name": "Love Like a Sunset, Pt. II", "uri": "spotify:track:4S5kWaB3e1dsgKBGgxfNgQ", "ms": 116720}, {"n": 5, "name": "Love Like a Sunset, Pt. II", "uri": "spotify:track:4S5kWaB3e1dsgKBGgxfNgQ", "ms": 116720}, {"n": 5, "name": "Love Like a Sunset, Pt. II", "uri": "spotify:track:4S5kWaB3e1dsgKBGgxfNgQ", "ms": 116720}, {"n": 6, "name": "Lasso", "uri": "spotify:track:3LENMSJJU0LLqcdVgf4JVW", "ms": 167840}, {"n": 6, "name": "Lasso", "uri": "spotify:track:3LENMSJJU0LLqcdVgf4JVW", "ms": 167840}, {"n": 6, "name": "Lasso", "uri": "spotify:track:3LENMSJJU0LLqcdVgf4JVW", "ms": 167840}, {"n": 6, "name": "Lasso", "uri": "spotify:track:3LENMSJJU0LLqcdVgf4JVW", "ms": 167840}, {"n": 7, "name": "Rome", "uri": "spotify:track:5BBR5jxgXXKXNHyAAyhOQr", "ms": 278080}, {"n": 7, "name": "Rome", "uri": "spotify:track:5BBR5jxgXXKXNHyAAyhOQr", "ms": 278080}, {"n": 7, "name": "Rome", "uri": "spotify:track:5BBR5jxgXXKXNHyAAyhOQr", "ms": 278080}, {"n": 7, "name": "Rome", "uri": "spotify:track:5BBR5jxgXXKXNHyAAyhOQr", "ms": 278080}, {"n": 8, "name": "Countdown", "uri": "spotify:track:025H4GJsBNxYd71QuiROQk", "ms": 237093}, {"n": 8, "name": "Countdown", "uri": "spotify:track:025H4GJsBNxYd71QuiROQk", "ms": 237093}, {"n": 8, "name": "Countdown", "uri": "spotify:track:025H4GJsBNxYd71QuiROQk", "ms": 237093}, {"n": 8, "name": "Countdown", "uri": "spotify:track:025H4GJsBNxYd71QuiROQk", "ms": 237093}, {"n": 9, "name": "Girlfriend", "uri": "spotify:track:6Z8I9zzJb5WCAJkz6qBo7k", "ms": 204106}, {"n": 9, "name": "Girlfriend", "uri": "spotify:track:6Z8I9zzJb5WCAJkz6qBo7k", "ms": 204106}, {"n": 9, "name": "Girlfriend", "uri": "spotify:track:6Z8I9zzJb5WCAJkz6qBo7k", "ms": 204106}, {"n": 9, "name": "Girlfriend", "uri": "spotify:track:6Z8I9zzJb5WCAJkz6qBo7k", "ms": 204106}, {"n": 10, "name": "Armistice", "uri": "spotify:track:49hvfrBDG4ig00wPmXLJRg", "ms": 185106}, {"n": 10, "name": "Armistice", "uri": "spotify:track:49hvfrBDG4ig00wPmXLJRg", "ms": 185106}, {"n": 10, "name": "Armistice", "uri": "spotify:track:49hvfrBDG4ig00wPmXLJRg", "ms": 185106}, {"n": 10, "name": "Armistice", "uri": "spotify:track:49hvfrBDG4ig00wPmXLJRg", "ms": 185106}], "spotify:album:7u6zL7kqpgLPISZYXNTgYk": [{"n": 1, "name": "Robot Rock / Oh Yeah", "uri": "spotify:track:5eS6pTvDNOvh2kyxeZtK3r", "ms": 387506}, {"n": 1, "name": "Robot Rock / Oh Yeah", "uri": "spotify:track:5eS6pTvDNOvh2kyxeZtK3r", "ms": 387506}, {"n": 2, "name": "Touch It / Technologic", "uri": "spotify:track:4IdiGMOzEYXOh2897XOV8i", "ms": 329653}, {"n": 2, "name": "Touch It / Technologic", "uri": "spotify:track:4IdiGMOzEYXOh2897XOV8i", "ms": 329653}, {"n": 3, "name": "Television Rules the Nation / Crescendolls", "uri": "spotify:track:1E8S3CSv20KrKT0C1yAjkO", "ms": 290840}, {"n": 3, "name": "Television Rules the Nation / Crescendolls", "uri": "spotify:track:1E8S3CSv20KrKT0C1yAjkO", "ms": 290840}, {"n": 4, "name": "Too Long / Steam Machine", "uri": "spotify:track:3n4ow4XGzwSIPxA3JHLF9p", "ms": 421600}, {"n": 4, "name": "Too Long / Steam Machine", "uri": "spotify:track:3n4ow4XGzwSIPxA3JHLF9p", "ms": 421600}, {"n": 5, "name": "Around the World / Harder, Better, Faster, Stronger", "uri": "spotify:track:5RByQFt9Mlo8hDYJ921tCv", "ms": 342626}, {"n": 5, "name": "Around the World / Harder, Better, Faster, Stronger", "uri": "spotify:track:5RByQFt9Mlo8hDYJ921tCv", "ms": 342626}, {"n": 6, "name": "Burnin' / Too Long", "uri": "spotify:track:3Ons6C3wXBMi8nYpLBMlVe", "ms": 431506}, {"n": 6, "name": "Burnin' / Too Long", "uri": "spotify:track:3Ons6C3wXBMi8nYpLBMlVe", "ms": 431506}, {"n": 7, "name": "Face to Face / Short Circuit", "uri": "spotify:track:5XzGyYZemDuCG3OdbhVFvh", "ms": 295226}, {"n": 7, "name": "Face to Face / Short Circuit", "uri": "spotify:track:5XzGyYZemDuCG3OdbhVFvh", "ms": 295226}, {"n": 8, "name": "One More Time / Aerodynamic", "uri": "spotify:track:1H1d4dr7Hk5Rrd8Tb5y5yr", "ms": 370533}, {"n": 8, "name": "One More Time / Aerodynamic", "uri": "spotify:track:1H1d4dr7Hk5Rrd8Tb5y5yr", "ms": 370533}, {"n": 9, "name": "Aerodynamic Beats / Gabrielle , Forget About the World", "uri": "spotify:track:0rFTPTXuVFIOYGnqXbWm3X", "ms": 211760}, {"n": 9, "name": "Aerodynamic Beats / Gabrielle , Forget About the World", "uri": "spotify:track:0rFTPTXuVFIOYGnqXbWm3X", "ms": 211760}, {"n": 10, "name": "Prime Time of Your Life / Brainwasher / Rollin' & Scratchin' / Alive", "uri": "spotify:track:3qVD67mL0JxgU0VQVKR52G", "ms": 622480}, {"n": 10, "name": "Prime Time of Your Life / Brainwasher / Rollin' & Scratchin' / Alive", "uri": "spotify:track:3qVD67mL0JxgU0VQVKR52G", "ms": 622480}, {"n": 11, "name": "Da Funk / Daftendirekt", "uri": "spotify:track:5OWhFeNXZ2RGbsGpl3rIc3", "ms": 396973}, {"n": 11, "name": "Da Funk / Daftendirekt", "uri": "spotify:track:5OWhFeNXZ2RGbsGpl3rIc3", "ms": 396973}, {"n": 12, "name": "Superheroes / Human After All / Rock'n Roll", "uri": "spotify:track:029O4HWI1pVXLfFdfQd1Jb", "ms": 341106}, {"n": 12, "name": "Superheroes / Human After All / Rock'n Roll", "uri": "spotify:track:029O4HWI1pVXLfFdfQd1Jb", "ms": 341106}, {"n": 13, "name": "Human After All / Together / One More Time / Music Sounds Better with You", "uri": "spotify:track:5q2KGgJV5l4MAnnGIrvKSK", "ms": 598666}, {"n": 13, "name": "Human After All / Together / One More Time / Music Sounds Better with You", "uri": "spotify:track:5q2KGgJV5l4MAnnGIrvKSK", "ms": 598666}]}