{"id":"04U9dg7w8k3a1NvJ7a71QL","name":"Happy Music Vol. 2","artist":"Various Artists","year":2009,"art":"https://i.scdn.co/image/ab67616d0000b27396d69686ae70dd90bcc937ec","tracks":[{"n":1,"d":1,"t":"Hockey Cokey","u":"spotify:track:36asYcC5ikHJIVUVRfcm60","dur":169280},{"n":2,"d":1,"t":"La Canzone Del Capitano","u":"spotify:track:5Murll5L4VSx6OC41lQ2Ok","dur":251533},{"n":3,"d":1,"t":"I Like To Move It, Move It","u":"spotify:track:7LB3RAzNv8ajFqJAdrFMeU","dur":239226},{"n":4,"d":1,"t":"Il Coccodrillo Come Fa?","u":"spotify:track:7G9RKCiLLiy1u6hlXKmWF2","dur":203506},{"n":5,"d":1,"t":"La Duena Del Swing","u":"spotify:track:3reDSFdShfUolje6Chz7KV","dur":260586},{"n":6,"d":1,"t":"La Vuelta","u":"spotify:track:7xHzRZX6AFo0DSC1TwD9bp","dur":210986},{"n":7,"d":1,"t":"Cuba","u":"spotify:track:7i66zIxmquwePGQYB44WnA","dur":187746},{"n":8,"d":1,"t":"Il Coccodrillo Come Fa - Karaoke Version","u":"spotify:track:72v7nhUyihnjrvxbpZFo8L","dur":198480},{"n":9,"d":1,"t":"Le Tagliatelle Di Nonna Pina - Karaoke Version","u":"spotify:track:6xpvbmi9cY9Uou3Psyr58L","dur":205400},{"n":10,"d":1,"t":"Dagen Ham","u":"spotify:track:6an7eP6SbjsFninioI6nV0","dur":326186}]}