{"id":"0v9wLVZmenxzVCQTyjSCTm","name":"Jaguar Sound","artist":"Adrian Quesada","year":2022,"art":"https://i.scdn.co/image/ab67616d0000b273977800500a88ed4380939f1d","tracks":[{"n":1,"d":1,"t":"Reflection with Two Children","u":"spotify:track:4GLZe2gim7DypwlyAFeE1j","dur":30374},{"n":2,"d":1,"t":"Noble Metals","u":"spotify:track:3vVJyxDwVf8FB9ACNra9Ec","dur":212000},{"n":3,"d":1,"t":"Rise of the Have Nots","u":"spotify:track:1u1bjQLf2I0Su0WovnIeSg","dur":295000},{"n":4,"d":1,"t":"Spirits","u":"spotify:track:1TIbURn4sgS0KX50sEI9bT","dur":225669},{"n":5,"d":1,"t":"Starry Nights","u":"spotify:track:5On9L7NCFzdWcmb7WCH0Op","dur":205067},{"n":6,"d":1,"t":"Alberto's Loop","u":"spotify:track:4bZrnzv3314qu4dmtVtPpB","dur":143044},{"n":7,"d":1,"t":"Portrait of the Artist as a Young Woman","u":"spotify:track:6oVCIRxQkPI8g20TcCXF4Q","dur":91002},{"n":8,"d":1,"t":"Fireflies","u":"spotify:track:15GFuoeUXLL3M7QiosNE90","dur":203002},{"n":9,"d":1,"t":"Turk's Cap","u":"spotify:track:5lBG9UjiDaZwDURjbBavBb","dur":190498},{"n":10,"d":1,"t":"The Inquisitor","u":"spotify:track:6F1yorNQmt4sOUMmmOBdGW","dur":193078},{"n":11,"d":1,"t":"DG on the Keys","u":"spotify:track:4TcQWFCfO1AL8AcmQd56Mq","dur":234853},{"n":12,"d":1,"t":"Final Portrait","u":"spotify:track:4dpVvHTc4YUYuiUcaNvK6o","dur":87500}]}