{"id":"1uFp52Q9EXLNA6DTRYnpTj","name":"The Velvet Rope","artist":"Janet Jackson","year":1997,"art":"https://i.scdn.co/image/ab67616d00001e022416d363e4220c21c5454efe","tracks":[{"n":1,"d":1,"t":"Interlude - Twisted Elegance","u":"spotify:track:4eYlbg0eWqcT9MNSA5SkcE","dur":42466},{"n":2,"d":1,"t":"Velvet Rope","u":"spotify:track:1cRksxRjmriJQPL70139cU","dur":295866},{"n":3,"d":1,"t":"You","u":"spotify:track:0SZYs2NtisS1fqSeBzItda","dur":282666},{"n":4,"d":1,"t":"Got 'Til It's Gone","u":"spotify:track:1EhvYd5e7vkoN3udEN1Vyl","dur":241760},{"n":5,"d":1,"t":"Interlude - Speaker Phone","u":"spotify:track:1TQCMEos6Hx3thNdPQKuEz","dur":54133},{"n":6,"d":1,"t":"My Need","u":"spotify:track:6brfFFQ1XpL2HFvY0mt5si","dur":224066},{"n":7,"d":1,"t":"Interlude - Fasten Your Seatbelts","u":"spotify:track:3f6CxJwss4Ujza2fElmkrq","dur":19106},{"n":8,"d":1,"t":"Go Deep","u":"spotify:track:1x3S3LYn5wqKHPzfUiqsj1","dur":282026},{"n":9,"d":1,"t":"Free Xone","u":"spotify:track:7EaJPOC3TRnZSciTK7X9HI","dur":297066},{"n":10,"d":1,"t":"Interlude - Memory","u":"spotify:track:037VN2sgj8lEpLdlxC1LB5","dur":4706},{"n":11,"d":1,"t":"Together Again","u":"spotify:track:1aJnGme5ZRltYTp8FJ52eZ","dur":301200},{"n":12,"d":1,"t":"Interlude - Online","u":"spotify:track:2G8qEteYTuudav3nqSKOcm","dur":19360},{"n":13,"d":1,"t":"Empty","u":"spotify:track:40irH4OCVWqOUwjN4IdCVt","dur":272733},{"n":14,"d":1,"t":"Interlude - Full","u":"spotify:track:6egW0L1fAKq1q6O0j19oBK","dur":12866},{"n":15,"d":1,"t":"What About","u":"spotify:track:0e5wVLmJukAySB1QxwqDtM","dur":264266},{"n":16,"d":1,"t":"Every Time","u":"spotify:track:4m6esDH7UC26ZfSQAaFG5e","dur":257105},{"n":17,"d":1,"t":"Tonight's The Night","u":"spotify:track:34rV39sdNLBQ2g1xYdqeMl","dur":307666},{"n":18,"d":1,"t":"I Get Lonely","u":"spotify:track:4FTq81I0X4J6y9X06GcZIN","dur":317560},{"n":19,"d":1,"t":"Rope Burn","u":"spotify:track:38KJYsWQrWJtS5XmZYLN3f","dur":255800},{"n":20,"d":1,"t":"Anything","u":"spotify:track:284luirv3Szbg1xGsLaeXv","dur":294840},{"n":21,"d":1,"t":"Interlude - Sad","u":"spotify:track:73sqX5y8diUgzIsJB58tCW","dur":10866},{"n":22,"d":1,"t":"Special","u":"spotify:track:7seA4KEZs3tXtsNlz4ZTSf","dur":202034},{"n":23,"d":1,"t":"Can't Be Stopped","u":"spotify:track:01S0QHvjqYXcBKTm8Rc8KT","dur":253990}]}