{"id":"5EEsbpPgWsbdYbZg3AxtsO","name":"Government Magic","artist":"Antibalas","year":2011,"art":"https://i.scdn.co/image/ab67616d0000b273fb08895c079de7d425389da7","tracks":[{"n":1,"d":1,"t":"Go Je Je","u":"spotify:track:1dDFysERIfgY3zxVpkCTLI","dur":398120},{"n":2,"d":1,"t":"Government Magic","u":"spotify:track:5THOhx0beHEhYeACQx5zpZ","dur":600026},{"n":3,"d":1,"t":"Out With The New In With The True","u":"spotify:track:7uf2r0nvysCxPWERNdX417","dur":297906},{"n":4,"d":1,"t":"Che Che Cole","u":"spotify:track:5KaNVtMkaanRibXwdM7qqb","dur":247760},{"n":5,"d":1,"t":"Dub Je Je","u":"spotify:track:4PNt6rT96tGjrXrDk6vece","dur":273800}]}