{"id":"5hZXbbvWKWfHbAKNgEDnS1","name":"Scott Ross: Complete Keyboard Works, Vol. 1","artist":"Essercizi","year":1985,"art":"https://i.scdn.co/image/ab67616d0000b273d40080b6bd515641620bb661","tracks":[{"n":1,"d":1,"t":"Scarlatti, D: Keyboard Sonata in D Minor, Kk. 1","u":"spotify:track:4UPuLjH1x5Z2E1tYMMeYdg","dur":167546},{"n":2,"d":1,"t":"Scarlatti, D: Keyboard Sonata in G Major, Kk. 2","u":"spotify:track:4G19HQgO5W6cvJvCukFWwY","dur":147293},{"n":3,"d":1,"t":"Scarlatti, D: Keyboard Sonata in A Minor, Kk. 3","u":"spotify:track:095GI9Q0W2Uhr556LKGR9O","dur":160986},{"n":4,"d":1,"t":"Scarlatti, D: Keyboard Sonata in G Minor, Kk. 4","u":"spotify:track:2pBA6zHs0RkxdXwAzMYCcl","dur":198960},{"n":5,"d":1,"t":"Scarlatti, D: Keyboard Sonata in D Minor, Kk. 5","u":"spotify:track:0CUDniyhhCAPvEq8iFfrVI","dur":183013},{"n":6,"d":1,"t":"Scarlatti, D: Keyboard Sonata in F Major, Kk. 6","u":"spotify:track:40iEVfd7v0u46C5aGczzG0","dur":190333},{"n":7,"d":1,"t":"Scarlatti, D: Keyboard Sonata in A Minor, Kk. 7","u":"spotify:track:6YPrKNx6ihtRNBrK0aorzQ","dur":269946},{"n":8,"d":1,"t":"Scarlatti, D: Keyboard Sonata in G Minor, Kk. 8","u":"spotify:track:1kgNVS7ab2RwbIJgs9ffIa","dur":164426},{"n":9,"d":1,"t":"Scarlatti, D: Keyboard Sonata in D Minor, Kk. 9","u":"spotify:track:6uvzcvFXEaHZKUOREbNW0m","dur":189533},{"n":10,"d":1,"t":"Scarlatti, D: Keyboard Sonata in D Minor, Kk. 10","u":"spotify:track:7HL7KEq1xoAtNm98izlgJk","dur":155933},{"n":11,"d":1,"t":"Scarlatti, D: Keyboard Sonata in C Minor, Kk. 11","u":"spotify:track:53Th16FdTNR39NKH5tmm5F","dur":147760},{"n":12,"d":1,"t":"Scarlatti, D: Keyboard Sonata in G Minor, Kk. 12","u":"spotify:track:4Hn9CHgakAksqYevJImW6R","dur":217600},{"n":13,"d":1,"t":"Scarlatti, D: Keyboard Sonata in G Major, Kk. 13","u":"spotify:track:01LiVKQCdi3svuhUaZyKWm","dur":278466},{"n":14,"d":1,"t":"Scarlatti, D: Keyboard Sonata in G Major, Kk. 14","u":"spotify:track:5cWEfo8i5bpFNFPydjLa7Y","dur":205773},{"n":15,"d":1,"t":"Scarlatti, D: Keyboard Sonata in E Minor, Kk. 15","u":"spotify:track:7r4mA0uU9YV9nn3qeigjfo","dur":198413},{"n":16,"d":1,"t":"Scarlatti, D: Keyboard Sonata in B-Flat Major, Kk. 16","u":"spotify:track:7c3w7oPun35XjEUnlrTROn","dur":280293},{"n":17,"d":1,"t":"Scarlatti, D: Keyboard Sonata in F Major, Kk. 17","u":"spotify:track:5L8p73wCXCxcQzOTcYkZoV","dur":187906},{"n":18,"d":1,"t":"Scarlatti, D: Keyboard Sonata in D Minor, Kk. 18","u":"spotify:track:0uQUww0Z7n4K5CNDNeS0Ra","dur":231200},{"n":19,"d":1,"t":"Scarlatti, D: Keyboard Sonata in F Minor, Kk. 19","u":"spotify:track:0vvMqfyHFwIp7r7LohzVXm","dur":254266},{"n":20,"d":1,"t":"Scarlatti, D: Keyboard Sonata in E Major, Kk. 20","u":"spotify:track:1FqGRr4hel5mBBEBjqdAzV","dur":202346},{"n":21,"d":1,"t":"Scarlatti, D: Keyboard Sonata in D Major, Kk. 21","u":"spotify:track:4YcgiHu3kzb3DANmkbW79p","dur":320133},{"n":22,"d":1,"t":"Scarlatti, D: Keyboard Sonata in C Minor, Kk. 22","u":"spotify:track:1hA3oW4VF41FX9swnIIUl3","dur":193666},{"n":23,"d":1,"t":"Scarlatti, D: Keyboard Sonata in D Major, Kk. 23","u":"spotify:track:1rYyKedzd2YbgGzAk2rt1O","dur":327066},{"n":24,"d":1,"t":"Scarlatti, D: Keyboard Sonata in A Major, Kk. 24","u":"spotify:track:6cXfsU3GIhnNDlPfwaIYFD","dur":319533},{"n":25,"d":1,"t":"Scarlatti, D: Keyboard Sonata in F-Sharp Minor, Kk. 25","u":"spotify:track:6kyPFmDDWdVrkHAfu0Gaeb","dur":223760},{"n":26,"d":1,"t":"Scarlatti, D: Keyboard Sonata in A Major, Kk. 26","u":"spotify:track:5uGKsJxiAupnCBM3MEwoDA","dur":267173},{"n":27,"d":1,"t":"Scarlatti, D: Keyboard Sonata in B Minor, Kk. 27","u":"spotify:track:772uzYAtSPUpXthvTTBijv","dur":262733},{"n":28,"d":1,"t":"Scarlatti, D: Keyboard Sonata in E Major, Kk. 28","u":"spotify:track:2RAYXRUftGqdW3yB5ETRwH","dur":228626},{"n":29,"d":1,"t":"Scarlatti, D: Keyboard Sonata in D Major, Kk. 29","u":"spotify:track:7k7BuaCombNuB3fPB6eFqg","dur":374653},{"n":30,"d":1,"t":"Scarlatti, D: Keyboard Sonata in G Minor, Kk. 30 \"Cat's Fugue\"","u":"spotify:track:1GMXzeDoXwmJlhpXxBEXSX","dur":254893}]}